cas_parser/__init__.py
cas_parser/_base_client.py
cas_parser/_client.py
cas_parser/_compat.py
cas_parser/_constants.py
cas_parser/_exceptions.py
cas_parser/_files.py
cas_parser/_models.py
cas_parser/_qs.py
cas_parser/_resource.py
cas_parser/_response.py
cas_parser/_streaming.py
cas_parser/_types.py
cas_parser/_version.py
cas_parser/py.typed
cas_parser/_utils/__init__.py
cas_parser/_utils/_compat.py
cas_parser/_utils/_datetime_parse.py
cas_parser/_utils/_logs.py
cas_parser/_utils/_proxy.py
cas_parser/_utils/_reflection.py
cas_parser/_utils/_resources_proxy.py
cas_parser/_utils/_streams.py
cas_parser/_utils/_sync.py
cas_parser/_utils/_transform.py
cas_parser/_utils/_typing.py
cas_parser/_utils/_utils.py
cas_parser/lib/.keep
cas_parser/resources/__init__.py
cas_parser/resources/cas_generator.py
cas_parser/resources/cas_parser.py
cas_parser/types/__init__.py
cas_parser/types/cas_generator_generate_cas_params.py
cas_parser/types/cas_generator_generate_cas_response.py
cas_parser/types/cas_parser_cams_kfintech_params.py
cas_parser/types/cas_parser_cdsl_params.py
cas_parser/types/cas_parser_nsdl_params.py
cas_parser/types/cas_parser_smart_parse_params.py
cas_parser/types/unified_response.py
cas_parser_python-1.1.0.dist-info/METADATA
cas_parser_python-1.1.0.dist-info/WHEEL
cas_parser_python-1.1.0.dist-info/licenses/LICENSE
cas_parser_python-1.1.0.dist-info/RECORD
